[{"content": {"Inputs": [{"name": "red", "type": "float", "value": "0.470692"}, {"name": "green", "type": "float", "value": "0.0489936"}, {"name": "blue", "type": "float", "value": "0.971948"}, {"name": "count", "type": "float", "value": "0"}], "Links": [{"dst_arg": "in1", "dst_node": "add", "src_arg": "red", "src_node": "Input"}, {"dst_arg": "in1", "dst_node": "add1", "src_arg": "green", "src_node": "Input"}, {"dst_arg": "in1", "dst_node": "add2", "src_arg": "blue", "src_node": "Input"}, {"dst_arg": "dst_red", "dst_node": "Output", "src_arg": "out", "src_node": "add"}, {"dst_arg": "dst_green", "dst_node": "Output", "src_arg": "out", "src_node": "add1"}, {"dst_arg": "dst_blue", "dst_node": "Output", "src_arg": "out", "src_node": "add2"}], "Nodes": {"add": {"args": [{"name": "in1", "type": "float", "value": "0.470692"}, {"name": "in2", "type": "float", "value": "0.001"}, {"name": "out", "type": "float", "value": "0.471692"}], "func_name": "Add", "priority": 0}, "add1": {"args": [{"name": "in1", "type": "float", "value": "0.0489936"}, {"name": "in2", "type": "float", "value": "0.0001"}, {"name": "out", "type": "float", "value": "0.0490936"}], "func_name": "Add", "priority": 0}, "add2": {"args": [{"name": "in1", "type": "float", "value": "0.971948"}, {"name": "in2", "type": "float", "value": "0.01"}, {"name": "out", "type": "float", "value": "0.981948"}], "func_name": "Add", "priority": 0}}, "Outputs": [{"name": "dst_red", "type": "float", "value": "0.471692"}, {"name": "dst_green", "type": "float", "value": "0.0490936"}, {"name": "dst_blue", "type": "float", "value": "0.981948"}]}, "pipeline_name": "fixed"}]